pyphot/README.md
pyphot/__init__.py
pyphot/config.py
pyphot/constants.py
pyphot/helpers.py
pyphot/legacy.py
pyphot/libraries.py
pyphot/licks.py
pyphot/pbar.py
pyphot/phot.py
pyphot/sun.py
pyphot/svo.py
pyphot/typing.py
pyphot/uncertain.py
pyphot/vega.py
pyphot/version.py
pyphot/io/__init__.py
pyphot/io/ascii.py
pyphot/io/fits.py
pyphot/io/hdf_h5py.py
pyphot/io/hdf_pytables.py
pyphot/io/header.py
pyphot/io/votable.py
pyphot/libs/alpha_lyr_mod_002.fits
pyphot/libs/alpha_lyr_mod_003.fits
pyphot/libs/alpha_lyr_mod_004.fits
pyphot/libs/alpha_lyr_stis_003.fits
pyphot/libs/alpha_lyr_stis_011.fits
pyphot/libs/licks.dat
pyphot/libs/new_filters.hd5
pyphot/libs/sun_kurucz93.fits
pyphot/libs/sun_reference_stis_001.fits
pyphot/libs/synphot_nonhst.hd5
pyphot/libs/vega.hd5
pyphot/libs/ascii_sources/2mass_h.csv
pyphot/libs/ascii_sources/2mass_j.csv
pyphot/libs/ascii_sources/2mass_ks.csv
pyphot/libs/ascii_sources/PS1_g.csv
pyphot/libs/ascii_sources/PS1_i.csv
pyphot/libs/ascii_sources/PS1_r.csv
pyphot/libs/ascii_sources/PS1_w.csv
pyphot/libs/ascii_sources/PS1_y.csv
pyphot/libs/ascii_sources/PS1_z.csv
pyphot/libs/ascii_sources/ZTF_g.csv
pyphot/libs/ascii_sources/ZTF_i.csv
pyphot/libs/ascii_sources/ZTF_r.csv
pyphot/libs/ascii_sources/cfht_cfh12k_cfh7406.csv
pyphot/libs/ascii_sources/cfht_cfh12k_cfh7504.csv
pyphot/libs/ascii_sources/cfht_megaprime_cfh7605.csv
pyphot/libs/ascii_sources/cfht_megaprime_cfh7701.csv
pyphot/libs/ascii_sources/cfht_megaprime_cfh7803.csv
pyphot/libs/ascii_sources/cfht_megaprime_cfh9301.csv
pyphot/libs/ascii_sources/cfht_megaprime_cfh9401.csv
pyphot/libs/ascii_sources/cfht_megaprime_cfh9601.csv
pyphot/libs/ascii_sources/cfht_megaprime_cfh9701.csv
pyphot/libs/ascii_sources/cfht_megaprime_cfh9702.csv
pyphot/libs/ascii_sources/cfht_megaprime_cfh9801.csv
pyphot/libs/ascii_sources/cfht_wircam_cfh8002.csv
pyphot/libs/ascii_sources/cfht_wircam_cfh8101.csv
pyphot/libs/ascii_sources/cfht_wircam_cfh8102.csv
pyphot/libs/ascii_sources/cfht_wircam_cfh8103.csv
pyphot-2.1.0.dist-info/licenses/LICENSE
pyphot-2.1.0.dist-info/METADATA
pyphot-2.1.0.dist-info/WHEEL
pyphot-2.1.0.dist-info/top_level.txt
pyphot-2.1.0.dist-info/RECORD
