Metadata-Version: 2.4
Name: pyphot
Version: 2.1.0
Summary: A tool for computing photometry from spectra
Author: Morgan Fouesneau
Classifier: Intended Audience :: Science/Research
Classifier: Operating System :: OS Independent
Classifier: Programming Language :: Python :: 3.9
Classifier: Programming Language :: Python :: 3.10
Classifier: Programming Language :: Python :: 3.11
Classifier: Programming Language :: Python :: 3.12
Classifier: Programming Language :: Python :: 3.13
Classifier: Programming Language :: Python :: 3.14
Classifier: License :: OSI Approved :: MIT License
Classifier: Topic :: Scientific/Engineering :: Astronomy
Requires-Python: >=3.9
License-File: LICENSE
Requires-Dist: numpy>1.6
Requires-Dist: scipy>0.9
Requires-Dist: astropy>5.0
Requires-Dist: pandas>=2.3.3
Requires-Dist: h5py>=3.14.0
Provides-Extra: testing
Requires-Dist: pytest; extra == "testing"
Requires-Dist: pytest-doctestplus; extra == "testing"
Requires-Dist: codecov; extra == "testing"
Requires-Dist: pytest-cov; extra == "testing"
Provides-Extra: ci
Requires-Dist: toml; extra == "ci"
Requires-Dist: ruff; extra == "ci"
Requires-Dist: isort; extra == "ci"
Requires-Dist: prek; extra == "ci"
Provides-Extra: docs
Requires-Dist: sphinx>=5.3; extra == "docs"
Requires-Dist: sphinx-book-theme>=0.3.3; extra == "docs"
Requires-Dist: sphinx-automodapi>=0.14; extra == "docs"
Requires-Dist: sphinx_copybutton>=0.5; extra == "docs"
Requires-Dist: sphinx-mdinclude>=0.6; extra == "docs"
Requires-Dist: sphinxcontrib-htmlhelp>=2.1.0; extra == "docs"
Requires-Dist: sphinxcontrib-serializinghtml>=2.0.0; extra == "docs"
Requires-Dist: sphinx-tabs>=3.0; extra == "docs"
Requires-Dist: myst-nb>=0.16.0; extra == "docs"
Requires-Dist: sphinx-design>=0.6; extra == "docs"
Requires-Dist: IPython>=8.0; extra == "docs"
Requires-Dist: matplotlib; extra == "docs"
Requires-Dist: numpydoc; extra == "docs"
Dynamic: license-file
